Metadata-Version: 2.1
Name: antiafk
Version: 1.0.0
Summary: Antiafk has been designed to utilize the pynput package by creating a cli that allows the user to specify a key to be to be triggered on interval.
Home-page: https://gitlab.com/rburns629/antiafk
Author: Robert Burns
Author-email: rburns629@gmail.com
License: MIT
Project-URL: Source, https://gitlab.com/rburns629/antiafk
Project-URL: Bug Reports, https://gitlab.com/rburns629/antiafk/issues
Keywords: cli wow world of warcraft classic afk keypress automated
Platform: UNKNOWN
Classifier: Development Status :: 5 - Production/Stable
Classifier: Intended Audience :: Developers
Classifier: Topic :: Software Development :: Build Tools
Classifier: License :: OSI Approved :: MIT License
Classifier: Programming Language :: Python :: 3.6
Classifier: Programming Language :: Python :: 3.7
